{
  "tasks": [
    {
      "id": 1767900269001,
      "status": "todo",
      "cat": "Comunicación",
      "title": "Boletines internos sobre avances CRPE (Enero de 2026)",
      "resp": "Profesional P1 Innovación",
      "sprint": "Sprint 1 (Ene 2026)"
    },
    {
      "id": 1767900269002,
      "status": "todo",
      "cat": "Gestión Ágil",
      "title": "Ceremonias de seguimiento de proyectos - TG (Semana 1)",
      "resp": "Profesional P1 Innovación",
      "sprint": "Sprint 1 (Ene 2026)"
    },
    {
      "id": 1767900269003,
      "status": "todo",
      "cat": "Gestión Ágil",
      "title": "Ceremonias de seguimiento de proyectos - TG (Semana 2)",
      "resp": "Profesional P1 Innovación",
      "sprint": "Sprint 1 (Ene 2026)"
    },
    {
      "id": 1767900269004,
      "status": "todo",
      "cat": "Gestión Ágil",
      "title": "Ceremonias de seguimiento de proyectos - TG (Semana 3)",
      "resp": "Profesional P1 Innovación",
      "sprint": "Sprint 1 (Ene 2026)"
    },
    {
      "id": 1767900269005,
      "status": "todo",
      "cat": "Gestión Ágil",
      "title": "Ceremonias de seguimiento de proyectos - TG (Semana 4)",
      "resp": "Profesional P1 Innovación",
      "sprint": "Sprint 1 (Ene 2026)"
    },
    {
      "id": 1767900269006,
      "status": "todo",
      "cat": "Gestión Ágil",
      "title": "Ceremonia de seguimiento de proyectos SafeGRID (Semana 1)",
      "resp": "Profesional P1 Innovación/ Profesional P1 Innovación Técnico",
      "sprint": "Sprint 1 (Ene 2026)"
    },
    {
      "id": 1767900269007,
      "status": "todo",
      "cat": "Gestión Ágil",
      "title": "Ceremonia de seguimiento de proyectos SafeGRID (Semana 2)",
      "resp": "Profesional P1 Innovación/ Profesional P1 Innovación Técnico",
      "sprint": "Sprint 1 (Ene 2026)"
    },
    {
      "id": 1767900269008,
      "status": "todo",
      "cat": "Gestión Ágil",
      "title": "Ceremonia de seguimiento de proyectos SafeGRID (Semana 3)",
      "resp": "Profesional P1 Innovación/ Profesional P1 Innovación Técnico",
      "sprint": "Sprint 1 (Ene 2026)"
    },
    {
      "id": 1767900269009,
      "status": "todo",
      "cat": "Gestión Ágil",
      "title": "Ceremonia de seguimiento de proyectos SafeGRID (Semana 4)",
      "resp": "Profesional P1 Innovación/ Profesional P1 Innovación Técnico",
      "sprint": "Sprint 1 (Ene 2026)"
    },
    {
      "id": 17679002694010,
      "status": "todo",
      "cat": "Gestión Ágil",
      "title": "Reunión con innovaitors para revisión de backlog prototipos (materiales, transformadores, liquidaciones)",
      "resp": "Profesional P1 Innovación",
      "sprint": "Sprint 1 (Ene 2026)"
    },
    {
      "id": 1767900269011,
      "status": "todo",
      "cat": "Gestión Ágil",
      "title": "Revisión backlog prototipos (materiales, transformadores, liquidaciones) en Drive enviado por innovaitors",
      "resp": "Profesional P1 Innovación/Practicante Universitario DevOps",
      "sprint": "Sprint 1 (Ene 2026)"
    },
    {
      "id": 1767900269012,
      "status": "todo",
      "cat": "Herramientas",
      "title": "Testeo prototipos (materiales, transformadores, liquidaciones)",
      "resp": "Profesional P1 Innovación/Practicante Universitario DevOps",
      "sprint": "Sprint 1 (Ene 2026)"
    },
    {
      "id": 1767900269013,
      "status": "todo",
      "cat": "Alineación",
      "title": "Preparación socialización proyecto SafeGRID con enfoque en impactos y estrategias de respuesta ante reclamos",
      "resp": "Profesional P1 Innovación/ Profesional P1 Innovación Técnico",
      "sprint": "Sprint 1 (Ene 2026)"
    },
    {
      "id": 1767900269014,
      "status": "todo",
      "cat": "Alineación",
      "title": "Reunión de verificación de estrategia para safeGRID (desde lo legal y temas de multas)",
      "resp": "Profesional P1 Innovación/ Profesional P1 Innovación Técnico",
      "sprint": "Sprint 1 (Ene 2026)"
    },
    {
      "id": 1767900269015,
      "status": "todo",
      "cat": "Comunicación",
      "title": "Boletines internos sobre avances CRPE (Febrero de 2026)",
      "resp": "Profesional P1 Innovación",
      "sprint": "Sprint 2 (Feb 2026)"
    },
    {
      "id": 1767900269016,
      "status": "todo",
      "cat": "Alineación",
      "title": "Reunión con gestión social - impactos SafeGRID",
      "resp": "Profesional P1 Innovación/ Profesional P1 Innovación Técnico",
      "sprint": "Sprint 2 (Feb 2026)"
    },
    {
      "id": 1767900269017,
      "status": "todo",
      "cat": "Alineación",
      "title": "Reunión con Cartera para revisar tema de usuarios electrodependientes - SafeGRID",
      "resp": "Profesional P1 Innovación/ Profesional P1 Innovación Técnico",
      "sprint": "Sprint 2 (Feb 2026)"
    },
    {
      "id": 1767900269018,
      "status": "todo",
      "cat": "Gestión Ágil",
      "title": "Acompañamiento en la instalación del prototipo SafeGRID (Primer PMV Ciudad Rodeo)",
      "resp": "Profesional P1 Innovación/ Profesional P1 Innovación Técnico",
      "sprint": "Sprint 2 (Feb 2026)"
    },
    {
      "id": 1767900269019,
      "status": "todo",
      "cat": "Comunicación",
      "title": "Preparación ficha técnica ANDESCO EE postulación SafeGRID",
      "resp": "Profesional P1 Innovación/ Profesional P1 Innovación Técnico",
      "sprint": "Sprint 2 (Feb 2026)"
    },
    {
      "id": 1767900269020,
      "status": "todo",
      "cat": "Gestión Ágil",
      "title": "Ceremonias de seguimiento de proyectos - TG (Semana 1)",
      "resp": "Profesional P1 Innovación",
      "sprint": "Sprint 2 (Feb 2026)"
    },
    {
      "id": 1767900269021,
      "status": "todo",
      "cat": "Gestión Ágil",
      "title": "Ceremonias de seguimiento de proyectos - TG (Semana 2)",
      "resp": "Profesional P1 Innovación",
      "sprint": "Sprint 2 (Feb 2026)"
    },
    {
      "id": 1767900269022,
      "status": "todo",
      "cat": "Gestión Ágil",
      "title": "Ceremonias de seguimiento de proyectos - TG (Semana 3)",
      "resp": "Profesional P1 Innovación",
      "sprint": "Sprint 2 (Feb 2026)"
    },
    {
      "id": 1767900269023,
      "status": "todo",
      "cat": "Gestión Ágil",
      "title": "Ceremonias de seguimiento de proyectos - TG (Semana 4)",
      "resp": "Profesional P1 Innovación",
      "sprint": "Sprint 2 (Feb 2026)"
    },
    {
      "id": 1767900269024,
      "status": "todo",
      "cat": "Estudios",
      "title": "Estudios sobre norma técnica asociada al core del negocio (remuneración y CRPE) (Semana 1)",
      "resp": "Profesional P1 Innovación",
      "sprint": "Sprint 2 (Feb 2026)"
    },
    {
      "id": 1767900269025,
      "status": "todo",
      "cat": "Estudios",
      "title": "Estudios sobre norma técnica asociada al core del negocio (remuneración y CRPE) (Semana 2)",
      "resp": "Profesional P1 Innovación",
      "sprint": "Sprint 2 (Feb 2026)"
    },
    {
      "id": 1767900269026,
      "status": "todo",
      "cat": "Estudios",
      "title": "Estudios sobre norma técnica asociada al core del negocio (remuneración y CRPE) (Semana 3)",
      "resp": "Profesional P1 Innovación",
      "sprint": "Sprint 2 (Feb 2026)"
    },
    {
      "id": 1767900269027,
      "status": "todo",
      "cat": "Estudios",
      "title": "Estudios sobre norma técnica asociada al core del negocio (remuneración y CRPE) (Semana 4)",
      "resp": "Profesional P1 Innovación",
      "sprint": "Sprint 2 (Feb 2026)"
    },
    {
      "id": 1767900269028,
      "status": "todo",
      "cat": "Gestión Ágil",
      "title": "Ceremonia de seguimiento de proyectos SafeGRID (Semana 1)",
      "resp": "Profesional P1 Innovación/ Profesional P1 Innovación Técnico",
      "sprint": "Sprint 2 (Feb 2026)"
    },
    {
      "id": 1767900269029,
      "status": "todo",
      "cat": "Gestión Ágil",
      "title": "Ceremonia de seguimiento de proyectos SafeGRID (Semana 2)",
      "resp": "Profesional P1 Innovación/ Profesional P1 Innovación Técnico",
      "sprint": "Sprint 2 (Feb 2026)"
    },
    {
      "id": 1767900269030,
      "status": "todo",
      "cat": "Gestión Ágil",
      "title": "Ceremonia de seguimiento de proyectos SafeGRID (Semana 3)",
      "resp": "Profesional P1 Innovación/ Profesional P1 Innovación Técnico",
      "sprint": "Sprint 2 (Feb 2026)"
    },
    {
      "id": 1767900269031,
      "status": "todo",
      "cat": "Gestión Ágil",
      "title": "Ceremonia de seguimiento de proyectos SafeGRID (Semana 4)",
      "resp": "Profesional P1 Innovación/ Profesional P1 Innovación Técnico",
      "sprint": "Sprint 2 (Feb 2026)"
    },
    {
      "id": 1767900269032,
      "status": "todo",
      "cat": "Herramientas",
      "title": "Testeo prototipos (materiales, transformadores, liquidaciones) (Semana 1 - 2)",
      "resp": "Profesional P1 Innovación/Practicante Universitario DevOps",
      "sprint": "Sprint 2 (Feb 2026)"
    },
    {
      "id": 1767900269033,
      "status": "todo",
      "cat": "Herramientas",
      "title": "Testeo prototipos (materiales, transformadores, liquidaciones) (Semana 3 - 4)",
      "resp": "Profesional P1 Innovación/Practicante Universitario DevOps",
      "sprint": "Sprint 2 (Feb 2026)"
    },
    {
      "id": 1767900269034,
      "status": "todo",
      "cat": "Vigilancia",
      "title": "Vigilancia tecnológica - CRPE (Mes 1)",
      "resp": "Profesional P1 Innovación",
      "sprint": "Sprint 2 (Feb 2026)"
    },
    {
      "id": 1767900269035,
      "status": "todo",
      "cat": "Comunicación",
      "title": "Boletines internos sobre avances CRPE (Marzo de 2026)",
      "resp": "Profesional P1 Innovación",
      "sprint": "Sprint 3 (Mar 2026)"
    },
    {
      "id": 1767900269036,
      "status": "todo",
      "cat": "Alineación",
      "title": "Sesión con gestores sociales CRPE",
      "resp": "Profesional P1 Innovación",
      "sprint": "Sprint 3 (Mar 2026)"
    },
    {
      "id": 1767900269037,
      "status": "todo",
      "cat": "Estudios",
      "title": "Estudios sobre norma técnica asociada al core del negocio (remuneración y CRPE) (Semana 1)",
      "resp": "Profesional P1 Innovación",
      "sprint": "Sprint 3 (Mar 2026)"
    },
    {
      "id": 1767900269038,
      "status": "todo",
      "cat": "Estudios",
      "title": "Estudios sobre norma técnica asociada al core del negocio (remuneración y CRPE) (Semana 2)",
      "resp": "Profesional P1 Innovación",
      "sprint": "Sprint 3 (Mar 2026)"
    },
    {
      "id": 1767900269039,
      "status": "todo",
      "cat": "Estudios",
      "title": "Estudios sobre norma técnica asociada al core del negocio (remuneración y CRPE) (Semana 3)",
      "resp": "Profesional P1 Innovación",
      "sprint": "Sprint 3 (Mar 2026)"
    },
    {
      "id": 1767900269040,
      "status": "todo",
      "cat": "Estudios",
      "title": "Estudios sobre norma técnica asociada al core del negocio (remuneración y CRPE) (Semana 4)",
      "resp": "Profesional P1 Innovación",
      "sprint": "Sprint 3 (Mar 2026)"
    },
    {
      "id": 1767900269041,
      "status": "todo",
      "cat": "Gestión Ágil",
      "title": "Ceremonia de seguimiento de proyectos SafeGRID (Semana 1)",
      "resp": "Profesional P1 Innovación/ Profesional P1 Innovación Técnico",
      "sprint": "Sprint 3 (Mar 2026)"
    },
    {
      "id": 1767900269042,
      "status": "todo",
      "cat": "Gestión Ágil",
      "title": "Ceremonia de seguimiento de proyectos SafeGRID (Semana 2)",
      "resp": "Profesional P1 Innovación/ Profesional P1 Innovación Técnico",
      "sprint": "Sprint 3 (Mar 2026)"
    },
    {
      "id": 1767900269043,
      "status": "todo",
      "cat": "Gestión Ágil",
      "title": "Ceremonia de seguimiento de proyectos SafeGRID (Semana 3)",
      "resp": "Profesional P1 Innovación/ Profesional P1 Innovación Técnico",
      "sprint": "Sprint 3 (Mar 2026)"
    },
    {
      "id": 1767900269044,
      "status": "todo",
      "cat": "Gestión Ágil",
      "title": "Ceremonia de seguimiento de proyectos SafeGRID (Semana 4)",
      "resp": "Profesional P1 Innovación/ Profesional P1 Innovación Técnico",
      "sprint": "Sprint 3 (Mar 2026)"
    },
    {
      "id": 1767900269045,
      "status": "todo",
      "cat": "Vigilancia",
      "title": "Vigilancia tecnológica - CRPE (Mes 2)",
      "resp": "Profesional P1 Innovación",
      "sprint": "Sprint 3 (Mar 2026)"
    },
    {
      "id": 1767900269046,
      "status": "todo",
      "cat": "Herramientas",
      "title": "Sesión testing MVP Materiales - detalle bugs y errores",
      "resp": "Profesional P1 Innovación/Practicante Universitario DevOps",
      "sprint": "Sprint 3 (Mar 2026)"
    },
    {
      "id": 1767900269047,
      "status": "todo",
      "cat": "Herramientas",
      "title": "Sesión testing MVP Liquidaciones - detalle bugs y errores",
      "resp": "Profesional P1 Innovación/Practicante Universitario DevOps",
      "sprint": "Sprint 3 (Mar 2026)"
    },
    {
      "id": 1767900269048,
      "status": "todo",
      "cat": "Herramientas",
      "title": "Sesión testing MVP Transformadores - detalle bugs y errores",
      "resp": "Profesional P1 Innovación/ Profesional P1 Innovación Técnico",
      "sprint": "Sprint 3 (Mar 2026)"
    },
    {
      "id": 1767900269049,
      "status": "todo",
      "cat": "Gestión Ágil",
      "title": "Acciones de cierre PBI - TG - ajustes finales al BI",
      "resp": "Profesional P1 Innovación/Practicante Universitario DevOps",
      "sprint": "Sprint 3 (Mar 2026)"
    },
    {
      "id": 1767900269050,
      "status": "todo",
      "cat": "Comunicación",
      "title": "Boletines internos sobre avances CRPE (Abril de 2026)",
      "resp": "Profesional P1 Innovación",
      "sprint": "Sprint 4 (Abr 2026)"
    },
    {
      "id": 1775489628951,
      "status": "todo",
      "cat": "Herramientas",
      "title": "Envío de feedback de testings a Innovaitors",
      "resp": "Profesional P1 Innovación/Practicante Universitario DevOps",
      "sprint": "Sprint 4 (Abr 2026)"
    },
    {
      "id": 1775489628952,
      "status": "todo",
      "cat": "Estudios",
      "title": "Estudios sobre norma técnica asociada al core del negocio (remuneración y CRPE) (Semana 1)",
      "resp": "Profesional P1 Innovación",
      "sprint": "Sprint 4 (Abr 2026)"
    },
    {
      "id": 1775489628953,
      "status": "todo",
      "cat": "Estudios",
      "title": "Estudios sobre norma técnica asociada al core del negocio (remuneración y CRPE) (Semana 2)",
      "resp": "Profesional P1 Innovación",
      "sprint": "Sprint 4 (Abr 2026)"
    },
    {
      "id": 1775489628954,
      "status": "todo",
      "cat": "Estudios",
      "title": "Estudios sobre norma técnica asociada al core del negocio (remuneración y CRPE) (Semana 3)",
      "resp": "Profesional P1 Innovación",
      "sprint": "Sprint 4 (Abr 2026)"
    },
    {
      "id": 1775489628955,
      "status": "todo",
      "cat": "Estudios",
      "title": "Estudios sobre norma técnica asociada al core del negocio (remuneración y CRPE) (Semana 4)",
      "resp": "Profesional P1 Innovación",
      "sprint": "Sprint 4 (Abr 2026)"
    },
    {
      "id": 1775489628956,
      "status": "todo",
      "cat": "Alineación",
      "title": "Sesión con gestora de comunicaciones CRPE - alineación de expectativas",
      "resp": "Profesional P1 Innovación",
      "sprint": "Sprint 4 (Abr 2026)"
    },
    {
      "id": 1775489628957,
      "status": "todo",
      "cat": "Alineación",
      "title": "Sesión con gestora de comunicaciones + Contact Center - alineación de expectativas",
      "resp": "Profesional P1 Innovación/Practicante Universitario DevOps",
      "sprint": "Sprint 4 (Abr 2026)"
    },
    {
      "id": 1775489628958,
      "status": "todo",
      "cat": "Alineación",
      "title": "Sesión con gestora de comunicaciones y coordinadora de canales - alcance apoyo DevOps de innovación",
      "resp": "Profesional P1 Innovación/Practicante Universitario DevOps",
      "sprint": "Sprint 4 (Abr 2026)"
    },
    {
      "id": 1775489628959,
      "status": "todo",
      "cat": "Gestión Ágil",
      "title": "Ceremonia de seguimiento de proyectos SafeGRID (Semana 1)",
      "resp": "Profesional P1 Innovación/ Profesional P1 Innovación Técnico",
      "sprint": "Sprint 4 (Abr 2026)"
    },
    {
      "id": 1775489628960,
      "status": "todo",
      "cat": "Gestión Ágil",
      "title": "Ceremonia de seguimiento de proyectos SafeGRID (Semana 2)",
      "resp": "Profesional P1 Innovación/ Profesional P1 Innovación Técnico",
      "sprint": "Sprint 4 (Abr 2026)"
    },
    {
      "id": 1775489628961,
      "status": "todo",
      "cat": "Gestión Ágil",
      "title": "Ceremonia de seguimiento de proyectos SafeGRID (Semana 3)",
      "resp": "Profesional P1 Innovación/ Profesional P1 Innovación Técnico",
      "sprint": "Sprint 4 (Abr 2026)"
    },
    {
      "id": 1775489628962,
      "status": "todo",
      "cat": "Gestión Ágil",
      "title": "Ceremonia de seguimiento de proyectos SafeGRID (Semana 4)",
      "resp": "Profesional P1 Innovación/ Profesional P1 Innovación Técnico",
      "sprint": "Sprint 4 (Abr 2026)"
    },
    {
      "id": 1775489628963,
      "status": "todo",
      "cat": "Herramientas",
      "title": "Construcción de agente de IA normativo y de CRPE (para consultas) en NotebookLM con enlace público para cualquier persona de CENS que quiera estudiar",
      "resp": "Profesional P1 Innovación",
      "sprint": "Sprint 4 (Abr 2026)"
    },
    {
      "id": 1775489628964,
      "status": "todo",
      "cat": "Vigilancia",
      "title": "Vigilancia tecnológica - CRPE (Mes 3)",
      "resp": "Profesional P1 Innovación",
      "sprint": "Sprint 4 (Abr 2026)"
    },
    {
      "id": 1775489628965,
      "status": "todo",
      "cat": "Alineación",
      "title": "Sesión con líder control pérdidas - revisión avances desde CENSNNOVA y alineación de expectativas",
      "resp": "Profesional P1 Innovación",
      "sprint": "Sprint 5 (May 2026)"
    },
    {
      "id": 1775489628966,
      "status": "todo",
      "cat": "Comunicación",
      "title": "Boletines internos sobre avances CRPE (Mayo de 2026)",
      "resp": "Profesional P1 Innovación",
      "sprint": "Sprint 5 (May 2026)"
    },
    {
      "id": 1775489628967,
      "status": "todo",
      "cat": "Estudios",
      "title": "Análisis estado CRPE en Colombia - investigación apalancada en motores de Perplexity AI Pro",
      "resp": "Profesional P1 Innovación",
      "sprint": "Sprint 5 (May 2026)"
    },
    {
      "id": 1775489628968,
      "status": "todo",
      "cat": "Vigilancia",
      "title": "Vigilancia tecnológica - CRPE (Mes 4)",
      "resp": "Profesional P1 Innovación",
      "sprint": "Sprint 5 (May 2026)"
    },
    {
      "id": 1775489628969,
      "status": "todo",
      "cat": "Gestión Ágil",
      "title": "Ceremonia de seguimiento de proyectos SafeGRID (Semana 1)",
      "resp": "Profesional P1 Innovación/ Profesional P1 Innovación Técnico",
      "sprint": "Sprint 5 (May 2026)"
    },
    {
      "id": 1775489628970,
      "status": "todo",
      "cat": "Gestión Ágil",
      "title": "Ceremonia de seguimiento de proyectos SafeGRID (Semana 2)",
      "resp": "Profesional P1 Innovación/ Profesional P1 Innovación Técnico",
      "sprint": "Sprint 5 (May 2026)"
    },
    {
      "id": 1775489628971,
      "status": "todo",
      "cat": "Gestión Ágil",
      "title": "Ceremonia de seguimiento de proyectos SafeGRID (Semana 3)",
      "resp": "Profesional P1 Innovación/ Profesional P1 Innovación Técnico",
      "sprint": "Sprint 5 (May 2026)"
    },
    {
      "id": 1775489628972,
      "status": "todo",
      "cat": "Gestión Ágil",
      "title": "Ceremonia de seguimiento de proyectos SafeGRID (Semana 4)",
      "resp": "Profesional P1 Innovación/ Profesional P1 Innovación Técnico",
      "sprint": "Sprint 5 (May 2026)"
    },
    {
      "id": 1775489628973,
      "status": "todo",
      "cat": "Herramientas",
      "title": "Ciclo de refactorización de prototipos PMV (Materiales, Transformadores, Liquidaciones) - (Semana 1)",
      "resp": "Profesional P1 Innovación/Practicante Universitario DevOps",
      "sprint": "Sprint 5 (May 2026)"
    },
    {
      "id": 1775489628974,
      "status": "todo",
      "cat": "Herramientas",
      "title": "Ciclo de refactorización de prototipos PMV (Materiales, Transformadores, Liquidaciones) - (Semana 2)",
      "resp": "Profesional P1 Innovación/Practicante Universitario DevOps",
      "sprint": "Sprint 5 (May 2026)"
    },
    {
      "id": 1775489628975,
      "status": "todo",
      "cat": "Herramientas",
      "title": "Ciclo de refactorización de prototipos PMV (Materiales, Transformadores, Liquidaciones) - (Semana 3)",
      "resp": "Profesional P1 Innovación/Practicante Universitario DevOps",
      "sprint": "Sprint 5 (May 2026)"
    },
    {
      "id": 1775489628976,
      "status": "todo",
      "cat": "Herramientas",
      "title": "Ciclo de refactorización de prototipos PMV (Materiales, Transformadores, Liquidaciones) - (Semana 4)",
      "resp": "Profesional P1 Innovación/Practicante Universitario DevOps",
      "sprint": "Sprint 5 (May 2026)"
    },
    {
      "id": 1775489628977,
      "status": "todo",
      "cat": "Comunicación",
      "title": "Postulación SafeGRID a los premios CIER de Innovación 2026",
      "resp": "Profesional P1 Innovación",
      "sprint": "Sprint 5 (May 2026)"
    },
    {
      "id": 1775489628978,
      "status": "todo",
      "cat": "Comunicación",
      "title": "Boletines internos sobre avances CRPE (Junio de 2026)",
      "resp": "Profesional P1 Innovación",
      "sprint": "Sprint 6 (Jun 2026)"
    },
    {
      "id": 1775489628979,
      "status": "todo",
      "cat": "Estudios",
      "title": "Análisis estado CRPE en Colombia - investigación apalancada en motores de Perplexity AI Pro",
      "resp": "Profesional P1 Innovación",
      "sprint": "Sprint 6 (Jun 2026)"
    },
    {
      "id": 1775489628980,
      "status": "todo",
      "cat": "Vigilancia",
      "title": "Vigilancia tecnológica - CRPE (Mes 5)",
      "resp": "Profesional P1 Innovación",
      "sprint": "Sprint 6 (Jun 2026)"
    },
    {
      "id": 1775489628981,
      "status": "todo",
      "cat": "Gestión Ágil",
      "title": "Ceremonia de seguimiento de proyectos SafeGRID (Semana 1)",
      "resp": "Profesional P1 Innovación/ Profesional P1 Innovación Técnico",
      "sprint": "Sprint 6 (Jun 2026)"
    },
    {
      "id": 1775489628982,
      "status": "todo",
      "cat": "Gestión Ágil",
      "title": "Ceremonia de seguimiento de proyectos SafeGRID (Semana 2)",
      "resp": "Profesional P1 Innovación/ Profesional P1 Innovación Técnico",
      "sprint": "Sprint 6 (Jun 2026)"
    },
    {
      "id": 1775489628983,
      "status": "todo",
      "cat": "Gestión Ágil",
      "title": "Ceremonia de seguimiento de proyectos SafeGRID (Semana 3)",
      "resp": "Profesional P1 Innovación/ Profesional P1 Innovación Técnico",
      "sprint": "Sprint 6 (Jun 2026)"
    },
    {
      "id": 1775489628984,
      "status": "todo",
      "cat": "Gestión Ágil",
      "title": "Ceremonia de seguimiento de proyectos SafeGRID (Semana 4)",
      "resp": "Profesional P1 Innovación/ Profesional P1 Innovación Técnico",
      "sprint": "Sprint 6 (Jun 2026)"
    },
    {
      "id": 1775489628985,
      "status": "todo",
      "cat": "Herramientas",
      "title": "Ciclo de refactorización de prototipos PMV (Materiales, Transformadores, Liquidaciones) - (Semana 1)",
      "resp": "Profesional P1 Innovación/Practicante Universitario DevOps",
      "sprint": "Sprint 6 (Jun 2026)"
    },
    {
      "id": 1775489628986,
      "status": "todo",
      "cat": "Herramientas",
      "title": "Ciclo de refactorización de prototipos PMV (Materiales, Transformadores, Liquidaciones) - (Semana 2)",
      "resp": "Profesional P1 Innovación/Practicante Universitario DevOps",
      "sprint": "Sprint 6 (Jun 2026)"
    },
    {
      "id": 1775489628987,
      "status": "todo",
      "cat": "Herramientas",
      "title": "Ciclo de refactorización de prototipos PMV (Materiales, Transformadores, Liquidaciones) - (Semana 3)",
      "resp": "Profesional P1 Innovación/Practicante Universitario DevOps",
      "sprint": "Sprint 6 (Jun 2026)"
    },
    {
      "id": 1775489628988,
      "status": "todo",
      "cat": "Herramientas",
      "title": "Ciclo de refactorización de prototipos PMV (Materiales, Transformadores, Liquidaciones) - (Semana 4)",
      "resp": "Profesional P1 Innovación/Practicante Universitario DevOps",
      "sprint": "Sprint 6 (Jun 2026)"
    }
  ],
  "sprints": [
    "Sprint 1 (Ene 2026)",
    "Sprint 2 (Feb 2026)",
    "Sprint 3 (Mar 2026)",
    "Sprint 4 (Abr 2026)",
    "Sprint 5 (May 2026)",
    "Sprint 6 (Jun 2026)",
    "Sprint 7 (Jul 2026)",
    "Sprint 8 (Ago 2026)",
    "Sprint 9 (Sept 2026)",
    "Sprint 10 (Oct 2026)",
    "Sprint 11 (Nov 2026)",
    "Sprint 12 (Dic 2026)"
  ],
  "cats": [
    "Alineación",
    "Comunicación",
    "Estudios",
    "Gestión Ágil",
    "Herramientas",
    "Vigilancia"
  ]
}